[
  {
    "date": "2026-04-08",
    "title": "When Everyone Else Stays Silent: 5 Quotes on Finding Your Voice",
    "theme": "courage",
    "theme_name": "Courage",
    "image": "listicles/2026-04-08.png",
    "items": [
      {
        "quote": "Courage is not the absence of fear. Courage is feeling fear, recognizing fear, and still taking action.",
        "source": "Discussions on Youth",
        "explanation": "True bravery means moving forward despite the butterflies in your stomach, not waiting until they disappear."
      },
      {
        "quote": "A great human revolution in just a single individual will help achieve a change in the destiny of a nation and, further, will enable a change in the destiny of all humankind.",
        "source": "The Human Revolution",
        "explanation": "Your personal transformation isn't selfish—it creates ripple effects that can change the world around you."
      },
      {
        "quote": "No matter what happens, I will not be defeated. I will not run away. I will not complain. I will not be negative. I will keep advancing.",
        "source": "The New Human Revolution, Vol. 1",
        "explanation": "When life knocks you down, this becomes your daily mantra for getting back up stronger."
      },
      {
        "quote": "Be the kind of person who, when your feet hit the floor in the morning, makes the devil say, 'Oh no, they're up!'",
        "source": "Youth and the Writings of Nichiren Daishonin",
        "explanation": "Start each day with such fierce determination that even your problems know they're in trouble."
      },
      {
        "quote": "The true hero is one who conquers his own anger and hatred.",
        "source": "For Today and Tomorrow",
        "explanation": "Real strength isn't overpowering others—it's mastering the negative emotions that try to control you."
      }
    ]
  }
]